{
  "schemas": [
    {
      "name": "TAC Cases",
      "prefix": "_0",
      "title": null,
      "description": null,
      "version": 33,
      "deleted": false,
      "id": 14051436,
      "form_options": {},
      "created_time": 1738709222216,
      "updated_time": 1740696867927,
      "icon_link": "https://d2lz1e868xzctj.cloudfront.net/icons/People.svg",
      "fields": [
        {
          "id": "1e5e83c8-bfee-42f2-92d7-b644570795c6",
          "name": "key",
          "label": "Key",
          "type": "PRIMARY",
          "position": 1,
          "required": true,
          "editable": true,
          "visible": true,
          "deleted": false,
          "placeholder": null,
          "hint": null,
          "field_options": {
            "unique": "true"
          },
          "filterable": true,
          "searchable": true,
          "has_dependents": false,
          "parent_id": null,
          "choices": [],
          "default": null,
          "validations": {}
        },
        {
          "id": "623c5fcf-443d-471b-993c-1cc152fac447",
          "name": "ticket",
          "label": "Ticket",
          "type": "RELATIONSHIP",
          "position": 2,
          "required": false,
          "editable": true,
          "visible": true,
          "deleted": false,
          "placeholder": null,
          "hint": null,
          "field_options": {
            "related_object_type": "NATIVE",
            "unique": "true"
          },
          "filterable": true,
          "searchable": true,
          "has_dependents": false,
          "parent_id": null,
          "related_entity_id": 1,
          "relationship_name": "ticket",
          "child_relationship_name": "tac_cases_1738709532346",
          "choices": [],
          "default": null,
          "validations": {}
        },
        {
          "id": "14ffad3a-709e-483e-931f-cf9a4810aa64",
          "name": "rma_needed",
          "label": "RMA Needed",
          "type": "CHECKBOX",
          "position": 3,
          "required": false,
          "editable": true,
          "visible": true,
          "deleted": false,
          "placeholder": null,
          "hint": null,
          "field_options": {
            "unique": "false"
          },
          "filterable": true,
          "searchable": true,
          "has_dependents": false,
          "parent_id": null,
          "choices": [],
          "default": null,
          "validations": {}
        },
        {
          "id": "7eb58324-e080-43d4-826b-2c057c2de9ab",
          "name": "installation_country",
          "label": "Installation Country",
          "type": "TEXT",
          "position": 4,
          "required": false,
          "editable": true,
          "visible": true,
          "deleted": false,
          "placeholder": null,
          "hint": null,
          "field_options": {
            "unique": "false"
          },
          "filterable": true,
          "searchable": true,
          "has_dependents": false,
          "parent_id": null,
          "choices": [],
          "default": null,
          "validations": {}
        },
        {
          "id": "a445d90a-d895-4dd4-adea-2d15dc0d9061",
          "name": "customer_tracking_number",
          "label": "Customer Tracking Number",
          "type": "TEXT",
          "position": 5,
          "required": false,
          "editable": true,
          "visible": true,
          "deleted": false,
          "placeholder": null,
          "hint": null,
          "field_options": {
            "unique": "false"
          },
          "filterable": true,
          "searchable": true,
          "has_dependents": false,
          "parent_id": null,
          "choices": [],
          "default": null,
          "validations": {}
        },
        {
          "id": "49acca1c-dc4f-4aa8-b64a-5a64ddb7f9df",
          "name": "contact_email",
          "label": "Contact Email",
          "type": "TEXT",
          "position": 6,
          "required": false,
          "editable": true,
          "visible": true,
          "deleted": false,
          "placeholder": null,
          "hint": null,
          "field_options": {
            "unique": "false"
          },
          "filterable": true,
          "searchable": true,
          "has_dependents": false,
          "parent_id": null,
          "choices": [],
          "default": null,
          "validations": {}
        },
        {
          "id": "e26a2b37-d2cc-4f68-b15e-fe3f36530cb8",
          "name": "product_name",
          "label": "Product Name",
          "type": "TEXT",
          "position": 7,
          "required": false,
          "editable": true,
          "visible": true,
          "deleted": false,
          "placeholder": null,
          "hint": null,
          "field_options": {
            "unique": "false"
          },
          "filterable": true,
          "searchable": true,
          "has_dependents": false,
          "parent_id": null,
          "choices": [],
          "default": null,
          "validations": {}
        },
        {
          "id": "fee8159d-cc29-4b8b-b2d1-8d83a04724df",
          "name": "product_serial_number",
          "label": "Product Serial Number",
          "type": "TEXT",
          "position": 8,
          "required": false,
          "editable": true,
          "visible": true,
          "deleted": false,
          "placeholder": null,
          "hint": null,
          "field_options": {
            "unique": "false"
          },
          "filterable": true,
          "searchable": true,
          "has_dependents": false,
          "parent_id": null,
          "choices": [],
          "default": null,
          "validations": {}
        },
        {
          "id": "fa1095a9-5ba6-4e33-9f8b-c0c9637fdf9f",
          "name": "faulty_part_number",
          "label": "Faulty Part Number",
          "type": "TEXT",
          "position": 9,
          "required": false,
          "editable": true,
          "visible": true,
          "deleted": false,
          "placeholder": null,
          "hint": null,
          "field_options": {
            "unique": "false"
          },
          "filterable": true,
          "searchable": true,
          "has_dependents": false,
          "parent_id": null,
          "choices": [],
          "default": null,
          "validations": {}
        },
        {
          "id": "513a21f1-7aa5-4832-94f2-627c34c2aa54",
          "name": "faulty_serial_number",
          "label": "Faulty Serial Number",
          "type": "TEXT",
          "position": 10,
          "required": false,
          "editable": true,
          "visible": true,
          "deleted": false,
          "placeholder": null,
          "hint": null,
          "field_options": {
            "unique": "false"
          },
          "filterable": true,
          "searchable": true,
          "has_dependents": false,
          "parent_id": null,
          "choices": [],
          "default": null,
          "validations": {}
        },
        {
          "id": "4c020ba3-b330-4ec8-a7a7-5926bbe5a86d",
          "name": "product_firmware_version",
          "label": "Product Firmware Version",
          "type": "TEXT",
          "position": 11,
          "required": false,
          "editable": true,
          "visible": true,
          "deleted": false,
          "placeholder": null,
          "hint": null,
          "field_options": {
            "unique": "false"
          },
          "filterable": true,
          "searchable": true,
          "has_dependents": false,
          "parent_id": null,
          "choices": [],
          "default": null,
          "validations": {}
        },
        {
          "id": "ec58558e-6cd1-4d92-81f0-116a4d70f18d",
          "name": "product_software_version",
          "label": "Product Software Version",
          "type": "TEXT",
          "position": 12,
          "required": false,
          "editable": true,
          "visible": true,
          "deleted": false,
          "placeholder": null,
          "hint": null,
          "field_options": {
            "unique": "false"
          },
          "filterable": true,
          "searchable": true,
          "has_dependents": false,
          "parent_id": null,
          "choices": [],
          "default": null,
          "validations": {}
        },
        {
          "id": "8cb706cb-1955-4b12-ab65-49ea0a54052e",
          "name": "case_solution_description",
          "label": "Case Solution Description",
          "type": "PARAGRAPH",
          "position": 13,
          "required": false,
          "editable": true,
          "visible": true,
          "deleted": false,
          "placeholder": null,
          "hint": null,
          "field_options": {
            "unique": "false"
          },
          "filterable": false,
          "searchable": true,
          "has_dependents": false,
          "parent_id": null,
          "choices": [],
          "default": null,
          "validations": {}
        },
        {
          "id": "2bf2cd85-85e9-47d9-9e97-8444a66f6e50",
          "name": "business_impact",
          "label": "Business Impact",
          "type": "TEXT",
          "position": 14,
          "required": false,
          "editable": true,
          "visible": true,
          "deleted": false,
          "placeholder": null,
          "hint": null,
          "field_options": {
            "unique": "false"
          },
          "filterable": true,
          "searchable": true,
          "has_dependents": false,
          "parent_id": null,
          "choices": [],
          "default": null,
          "validations": {}
        },
        {
          "id": "120eee54-2b15-4a8c-a955-311819366a3f",
          "name": "account_number",
          "label": "Account Number",
          "type": "TEXT",
          "position": 15,
          "required": false,
          "editable": true,
          "visible": true,
          "deleted": false,
          "placeholder": null,
          "hint": null,
          "field_options": {
            "unique": "false"
          },
          "filterable": true,
          "searchable": true,
          "has_dependents": false,
          "parent_id": null,
          "choices": [],
          "default": null,
          "validations": {}
        },
        {
          "id": "22be3a1e-fd98-45ce-941e-e9c2863c3a65",
          "name": "case_owner",
          "label": "Case Owner",
          "type": "TEXT",
          "position": 16,
          "required": false,
          "editable": true,
          "visible": true,
          "deleted": false,
          "placeholder": null,
          "hint": null,
          "field_options": {
            "unique": "false"
          },
          "filterable": true,
          "searchable": true,
          "has_dependents": false,
          "parent_id": null,
          "choices": [],
          "default": null,
          "validations": {}
        },
        {
          "id": "478d45d8-853a-42ba-b4e8-a6f94bd584eb",
          "name": "case_number",
          "label": "Case Number",
          "type": "TEXT",
          "position": 17,
          "required": false,
          "editable": true,
          "visible": true,
          "deleted": false,
          "placeholder": null,
          "hint": null,
          "field_options": {
            "unique": "false"
          },
          "filterable": true,
          "searchable": true,
          "has_dependents": false,
          "parent_id": null,
          "choices": [],
          "default": null,
          "validations": {}
        },
        {
          "id": "7544cbf6-e430-4be0-a88e-cd80ee02e35d",
          "name": "related_dispatch_count",
          "label": "Related Dispatch Count",
          "type": "NUMBER",
          "position": 18,
          "required": false,
          "editable": true,
          "visible": true,
          "deleted": false,
          "placeholder": null,
          "hint": null,
          "field_options": {
            "unique": "false"
          },
          "filterable": true,
          "searchable": true,
          "has_dependents": false,
          "parent_id": null,
          "choices": [],
          "default": null,
          "validations": {}
        }
      ]
    },
    {
      "name": "RMA Cases",
      "prefix": "_1",
      "title": null,
      "description": null,
      "version": 147,
      "deleted": false,
      "id": 14052721,
      "form_options": {},
      "created_time": 1738710431638,
      "updated_time": 1741660377671,
      "icon_link": "https://d2lz1e868xzctj.cloudfront.net/icons/Equipment.svg",
      "fields": [
        {
          "id": "7b41622e-bf66-4f7a-be51-351eb43ae4f3",
          "name": "key",
          "label": "Key",
          "type": "PRIMARY",
          "position": 1,
          "required": true,
          "editable": true,
          "visible": true,
          "deleted": false,
          "placeholder": null,
          "hint": null,
          "field_options": {
            "unique": "true"
          },
          "filterable": true,
          "searchable": true,
          "has_dependents": false,
          "parent_id": null,
          "choices": [],
          "default": null,
          "validations": {}
        },
        {
          "id": "64433d89-2baa-40e7-a4f0-692ea66a47db",
          "name": "ticket",
          "label": "Ticket",
          "type": "RELATIONSHIP",
          "position": 2,
          "required": false,
          "editable": true,
          "visible": true,
          "deleted": false,
          "placeholder": null,
          "hint": null,
          "field_options": {
            "related_object_type": "NATIVE",
            "unique": "true"
          },
          "filterable": true,
          "searchable": true,
          "has_dependents": false,
          "parent_id": null,
          "related_entity_id": 1,
          "relationship_name": "ticket",
          "child_relationship_name": "rma_cases_1738710512736",
          "choices": [],
          "default": null,
          "validations": {}
        },
        {
          "id": "81173c7a-0f1d-4945-82fb-0ddd0b59b127",
          "name": "tac_case",
          "label": "TAC Case",
          "type": "RELATIONSHIP",
          "position": 3,
          "required": false,
          "editable": true,
          "visible": true,
          "deleted": false,
          "placeholder": null,
          "hint": null,
          "field_options": {
            "unique": "false"
          },
          "filterable": true,
          "searchable": true,
          "has_dependents": false,
          "parent_id": null,
          "related_entity_id": 14051436,
          "relationship_name": "tac_case",
          "child_relationship_name": "rma_cases_1738710573841",
          "choices": [],
          "default": null,
          "validations": {}
        },
        {
          "id": "9ba2dc6b-7e30-454f-9755-f2e1f8e3e242",
          "name": "request_type",
          "label": "Request Type",
          "type": "TEXT",
          "position": 4,
          "required": false,
          "editable": true,
          "visible": true,
          "deleted": false,
          "placeholder": null,
          "hint": null,
          "field_options": {
            "unique": "false"
          },
          "filterable": true,
          "searchable": true,
          "has_dependents": false,
          "parent_id": null,
          "choices": [],
          "default": null,
          "validations": {}
        },
        {
          "id": "0286e55e-be39-458d-8f0d-45cddbbda46c",
          "name": "new_part_number",
          "label": "New Part Number",
          "type": "TEXT",
          "position": 5,
          "required": false,
          "editable": true,
          "visible": true,
          "deleted": false,
          "placeholder": null,
          "hint": null,
          "field_options": {
            "unique": "false"
          },
          "filterable": true,
          "searchable": true,
          "has_dependents": false,
          "parent_id": null,
          "choices": [],
          "default": null,
          "validations": {}
        },
        {
          "id": "ef9d8913-84f2-41ff-97a1-373cf2127df2",
          "name": "new_part_serial_number",
          "label": "New Part Serial Number",
          "type": "TEXT",
          "position": 6,
          "required": false,
          "editable": true,
          "visible": true,
          "deleted": false,
          "placeholder": null,
          "hint": null,
          "field_options": {
            "unique": "false"
          },
          "filterable": true,
          "searchable": true,
          "has_dependents": false,
          "parent_id": null,
          "choices": [],
          "default": null,
          "validations": {}
        },
        {
          "id": "18afd8d6-2eda-4dc9-9ede-7bb452e71a53",
          "name": "faulty_part_number",
          "label": "Faulty Part Number",
          "type": "TEXT",
          "position": 7,
          "required": false,
          "editable": true,
          "visible": true,
          "deleted": false,
          "placeholder": null,
          "hint": null,
          "field_options": {
            "unique": "false"
          },
          "filterable": true,
          "searchable": true,
          "has_dependents": false,
          "parent_id": null,
          "choices": [],
          "default": null,
          "validations": {}
        },
        {
          "id": "d601b666-0b2d-43fe-8882-3057bded322c",
          "name": "faulty_serial_number",
          "label": "Faulty Serial Number",
          "type": "TEXT",
          "position": 8,
          "required": false,
          "editable": true,
          "visible": true,
          "deleted": false,
          "placeholder": null,
          "hint": null,
          "field_options": {
            "unique": "false"
          },
          "filterable": true,
          "searchable": true,
          "has_dependents": false,
          "parent_id": null,
          "choices": [],
          "default": null,
          "validations": {}
        },
        {
          "id": "62e6381e-bb12-4b33-98a0-89dca11b5b05",
          "name": "returned_part_number",
          "label": "Returned Part Number",
          "type": "TEXT",
          "position": 9,
          "required": false,
          "editable": true,
          "visible": true,
          "deleted": false,
          "placeholder": null,
          "hint": null,
          "field_options": {
            "unique": "false"
          },
          "filterable": true,
          "searchable": true,
          "has_dependents": false,
          "parent_id": null,
          "choices": [],
          "default": null,
          "validations": {}
        },
        {
          "id": "3e9adeaa-c016-4d61-9892-eb0c613e2ede",
          "name": "returned_serial_number",
          "label": "Returned Serial Number",
          "type": "TEXT",
          "position": 10,
          "required": false,
          "editable": true,
          "visible": true,
          "deleted": false,
          "placeholder": null,
          "hint": null,
          "field_options": {
            "unique": "false"
          },
          "filterable": true,
          "searchable": true,
          "has_dependents": false,
          "parent_id": null,
          "choices": [],
          "default": null,
          "validations": {}
        },
        {
          "id": "c451d2db-6439-402a-852f-7b93dce70fc4",
          "name": "new_part_shipped_date",
          "label": "New Part Shipped Date",
          "type": "TEXT",
          "position": 11,
          "required": false,
          "editable": true,
          "visible": true,
          "deleted": false,
          "placeholder": null,
          "hint": null,
          "field_options": {
            "unique": "false"
          },
          "filterable": true,
          "searchable": true,
          "has_dependents": false,
          "parent_id": null,
          "choices": [],
          "default": null,
          "validations": {}
        },
        {
          "id": "4852f7f3-5d97-4074-b1b6-c0539827651e",
          "name": "new_part_delivered_date",
          "label": "New Part Delivered Date",
          "type": "TEXT",
          "position": 12,
          "required": false,
          "editable": true,
          "visible": true,
          "deleted": false,
          "placeholder": null,
          "hint": null,
          "field_options": {
            "unique": "false"
          },
          "filterable": true,
          "searchable": true,
          "has_dependents": false,
          "parent_id": null,
          "choices": [],
          "default": null,
          "validations": {}
        },
        {
          "id": "d48461a2-cac5-4427-b0e1-e5d9871441e2",
          "name": "faulty_part_shipped_date",
          "label": "Faulty Part Shipped Date",
          "type": "TEXT",
          "position": 13,
          "required": false,
          "editable": true,
          "visible": true,
          "deleted": false,
          "placeholder": null,
          "hint": null,
          "field_options": {
            "unique": "false"
          },
          "filterable": true,
          "searchable": true,
          "has_dependents": false,
          "parent_id": null,
          "choices": [],
          "default": null,
          "validations": {}
        },
        {
          "id": "34d34130-cf51-4665-894e-83fcc3461d8b",
          "name": "faulty_part_delivered_date",
          "label": "Faulty Part Delivered Date",
          "type": "TEXT",
          "position": 14,
          "required": false,
          "editable": true,
          "visible": true,
          "deleted": false,
          "placeholder": null,
          "hint": null,
          "field_options": {
            "unique": "false"
          },
          "filterable": true,
          "searchable": true,
          "has_dependents": false,
          "parent_id": null,
          "choices": [],
          "default": null,
          "validations": {}
        },
        {
          "id": "5a8f8845-f3b1-4895-8ab9-d7673c75876d",
          "name": "failure_analysis_start_date",
          "label": "Failure Analysis Start Date",
          "type": "TEXT",
          "position": 15,
          "required": false,
          "editable": true,
          "visible": true,
          "deleted": false,
          "placeholder": null,
          "hint": null,
          "field_options": {
            "unique": "false"
          },
          "filterable": true,
          "searchable": true,
          "has_dependents": false,
          "parent_id": null,
          "choices": [],
          "default": null,
          "validations": {}
        },
        {
          "id": "1567d34a-f59f-4da6-8648-cb9b915f675c",
          "name": "failure_analysis_in_progress_date",
          "label": "Failure Analysis In Progress Date",
          "type": "TEXT",
          "position": 16,
          "required": false,
          "editable": true,
          "visible": true,
          "deleted": false,
          "placeholder": null,
          "hint": null,
          "field_options": {
            "unique": "false"
          },
          "filterable": false,
          "searchable": true,
          "has_dependents": false,
          "parent_id": null,
          "choices": [],
          "default": null,
          "validations": {}
        },
        {
          "id": "732b0583-40ed-430c-a128-1507b298578d",
          "name": "failure_analysis_finished_date",
          "label": "Failure Analysis Finished Date",
          "type": "TEXT",
          "position": 17,
          "required": false,
          "editable": true,
          "visible": true,
          "deleted": false,
          "placeholder": null,
          "hint": null,
          "field_options": {
            "unique": "false"
          },
          "filterable": true,
          "searchable": true,
          "has_dependents": false,
          "parent_id": null,
          "choices": [],
          "default": null,
          "validations": {}
        },
        {
          "id": "c52c867f-d40a-42f4-a608-5b53f43fbc4d",
          "name": "ship_to_street1",
          "label": "Ship To Street1",
          "type": "TEXT",
          "position": 18,
          "required": false,
          "editable": true,
          "visible": true,
          "deleted": false,
          "placeholder": null,
          "hint": null,
          "field_options": {
            "unique": "false"
          },
          "filterable": true,
          "searchable": true,
          "has_dependents": false,
          "parent_id": null,
          "choices": [],
          "default": null,
          "validations": {}
        },
        {
          "id": "d7abbc31-24e3-45bc-81aa-c819d60c04f8",
          "name": "ship_to_city",
          "label": "Ship To City",
          "type": "TEXT",
          "position": 19,
          "required": false,
          "editable": true,
          "visible": true,
          "deleted": false,
          "placeholder": null,
          "hint": null,
          "field_options": {
            "unique": "false"
          },
          "filterable": true,
          "searchable": true,
          "has_dependents": false,
          "parent_id": null,
          "choices": [],
          "default": null,
          "validations": {}
        },
        {
          "id": "3dd6a68e-e68b-460d-a783-22d1a3fab9f5",
          "name": "ship_to_province",
          "label": "Ship To Province",
          "type": "TEXT",
          "position": 20,
          "required": false,
          "editable": true,
          "visible": true,
          "deleted": false,
          "placeholder": null,
          "hint": null,
          "field_options": {
            "unique": "false"
          },
          "filterable": true,
          "searchable": true,
          "has_dependents": false,
          "parent_id": null,
          "choices": [],
          "default": null,
          "validations": {}
        },
        {
          "id": "9c511e9d-5d1f-4727-9ae5-e9dc05a14edb",
          "name": "ship_to_country",
          "label": "Ship To Country",
          "type": "TEXT",
          "position": 21,
          "required": false,
          "editable": true,
          "visible": true,
          "deleted": false,
          "placeholder": null,
          "hint": null,
          "field_options": {
            "unique": "false"
          },
          "filterable": true,
          "searchable": true,
          "has_dependents": false,
          "parent_id": null,
          "choices": [],
          "default": null,
          "validations": {}
        },
        {
          "id": "30e2b612-a6e2-46a1-9d35-cf8ecba88a77",
          "name": "ship_to_postal_code",
          "label": "Ship To Postal Code",
          "type": "TEXT",
          "position": 22,
          "required": false,
          "editable": true,
          "visible": true,
          "deleted": false,
          "placeholder": null,
          "hint": null,
          "field_options": {
            "unique": "false"
          },
          "filterable": true,
          "searchable": true,
          "has_dependents": false,
          "parent_id": null,
          "choices": [],
          "default": null,
          "validations": {}
        },
        {
          "id": "584612ad-79e7-4b4b-a094-9bf57267c9e7",
          "name": "ship_to_attention",
          "label": "Ship To Attention",
          "type": "TEXT",
          "position": 23,
          "required": false,
          "editable": true,
          "visible": true,
          "deleted": false,
          "placeholder": null,
          "hint": null,
          "field_options": {
            "unique": "false"
          },
          "filterable": true,
          "searchable": true,
          "has_dependents": false,
          "parent_id": null,
          "choices": [],
          "default": null,
          "validations": {}
        },
        {
          "id": "24e9456f-4a7a-482a-b876-27ce09968d3f",
          "name": "ship_to_phone",
          "label": "Ship To Phone",
          "type": "TEXT",
          "position": 24,
          "required": false,
          "editable": true,
          "visible": true,
          "deleted": false,
          "placeholder": null,
          "hint": null,
          "field_options": {
            "unique": "false"
          },
          "filterable": true,
          "searchable": true,
          "has_dependents": false,
          "parent_id": null,
          "choices": [],
          "default": null,
          "validations": {}
        },
        {
          "id": "5ca66147-5fef-4be4-bbd0-487351fb8828",
          "name": "ship_to_contact_email",
          "label": "Ship To Contact Email",
          "type": "TEXT",
          "position": 25,
          "required": false,
          "editable": true,
          "visible": true,
          "deleted": false,
          "placeholder": null,
          "hint": null,
          "field_options": {
            "unique": "false"
          },
          "filterable": true,
          "searchable": true,
          "has_dependents": false,
          "parent_id": null,
          "choices": [],
          "default": null,
          "validations": {}
        },
        {
          "id": "10b211d6-e1d3-4b9a-87f9-f863ef15aad0",
          "name": "shipped_carrier",
          "label": "Shipped Carrier",
          "type": "TEXT",
          "position": 26,
          "required": false,
          "editable": true,
          "visible": true,
          "deleted": false,
          "placeholder": null,
          "hint": null,
          "field_options": {
            "unique": "false"
          },
          "filterable": false,
          "searchable": true,
          "has_dependents": false,
          "parent_id": null,
          "choices": [],
          "default": null,
          "validations": {}
        },
        {
          "id": "52376603-0199-458a-8ed8-1de68ec565dc",
          "name": "vendor_rma_number",
          "label": "Vendor Rma Number",
          "type": "TEXT",
          "position": 27,
          "required": false,
          "editable": true,
          "visible": true,
          "deleted": false,
          "placeholder": null,
          "hint": null,
          "field_options": {
            "unique": "false"
          },
          "filterable": false,
          "searchable": true,
          "has_dependents": false,
          "parent_id": null,
          "choices": [],
          "default": null,
          "validations": {}
        },
        {
          "id": "e5eaa14b-b258-4f1b-9d43-c15e7c70de9b",
          "name": "installation_country",
          "label": "Installation Country",
          "type": "TEXT",
          "position": 28,
          "required": false,
          "editable": true,
          "visible": true,
          "deleted": false,
          "placeholder": null,
          "hint": null,
          "field_options": {
            "unique": "false"
          },
          "filterable": false,
          "searchable": true,
          "has_dependents": false,
          "parent_id": null,
          "choices": [],
          "default": null,
          "validations": {}
        },
        {
          "id": "d68cc617-0aa0-4a59-8dd3-2c15e7a4cd29",
          "name": "customer_tracking_number",
          "label": "Customer Tracking Number",
          "type": "TEXT",
          "position": 29,
          "required": false,
          "editable": true,
          "visible": true,
          "deleted": false,
          "placeholder": null,
          "hint": null,
          "field_options": {
            "unique": "false"
          },
          "filterable": false,
          "searchable": true,
          "has_dependents": false,
          "parent_id": null,
          "choices": [],
          "default": null,
          "validations": {}
        },
        {
          "id": "5e02b54f-c011-4572-9da1-64bb4282b2fa",
          "name": "vendor_tracking_number",
          "label": "Vendor Tracking Number",
          "type": "TEXT",
          "position": 30,
          "required": false,
          "editable": true,
          "visible": true,
          "deleted": false,
          "placeholder": null,
          "hint": null,
          "field_options": {
            "unique": "false"
          },
          "filterable": false,
          "searchable": true,
          "has_dependents": false,
          "parent_id": null,
          "choices": [],
          "default": null,
          "validations": {}
        },
        {
          "id": "307fe503-a875-488a-b0fd-064a6b14390c",
          "name": "new_part_delivery_date_eta",
          "label": "New Part Delivery Date Eta",
          "type": "TEXT",
          "position": 31,
          "required": false,
          "editable": true,
          "visible": true,
          "deleted": false,
          "placeholder": null,
          "hint": null,
          "field_options": {
            "unique": "false"
          },
          "filterable": true,
          "searchable": true,
          "has_dependents": false,
          "parent_id": null,
          "choices": [],
          "default": null,
          "validations": {}
        },
        {
          "id": "7cec6eae-c45b-488d-a5ac-5d66fab4af23",
          "name": "contact_email",
          "label": "Contact Email",
          "type": "TEXT",
          "position": 32,
          "required": false,
          "editable": true,
          "visible": true,
          "deleted": false,
          "placeholder": null,
          "hint": null,
          "field_options": {
            "unique": "false"
          },
          "filterable": false,
          "searchable": true,
          "has_dependents": false,
          "parent_id": null,
          "choices": [],
          "default": null,
          "validations": {}
        },
        {
          "id": "0c3605cb-aa77-4686-9454-cd0edf782ea1",
          "name": "ship_to_party",
          "label": "Ship To Party",
          "type": "TEXT",
          "position": 33,
          "required": false,
          "editable": true,
          "visible": true,
          "deleted": false,
          "placeholder": null,
          "hint": null,
          "field_options": {
            "unique": "false"
          },
          "filterable": false,
          "searchable": true,
          "has_dependents": false,
          "parent_id": null,
          "choices": [],
          "default": null,
          "validations": {}
        },
        {
          "id": "1b1e3b37-fef1-4354-a49d-f558ce37b8fd",
          "name": "inbound_id",
          "label": "Inbound ID",
          "type": "TEXT",
          "position": 34,
          "required": false,
          "editable": true,
          "visible": true,
          "deleted": false,
          "placeholder": null,
          "hint": null,
          "field_options": {
            "unique": "false"
          },
          "filterable": true,
          "searchable": true,
          "has_dependents": false,
          "parent_id": null,
          "choices": [],
          "default": null,
          "validations": {}
        },
        {
          "id": "7320afae-ede4-4ebc-9557-ede010b4d066",
          "name": "device_name",
          "label": "Device Name",
          "type": "TEXT",
          "position": 35,
          "required": false,
          "editable": true,
          "visible": true,
          "deleted": false,
          "placeholder": null,
          "hint": null,
          "field_options": {
            "unique": "false"
          },
          "filterable": false,
          "searchable": true,
          "has_dependents": false,
          "parent_id": null,
          "choices": [],
          "default": null,
          "validations": {}
        },
        {
          "id": "fc710f6c-2831-451b-9f30-ed63a9138eaf",
          "name": "case_number",
          "label": "Case Number",
          "type": "TEXT",
          "position": 36,
          "required": false,
          "editable": true,
          "visible": true,
          "deleted": false,
          "placeholder": null,
          "hint": null,
          "field_options": {
            "unique": "false"
          },
          "filterable": true,
          "searchable": true,
          "has_dependents": false,
          "parent_id": null,
          "choices": [],
          "default": null,
          "validations": {}
        }
      ]
    }
  ]
}
